.gitignore
.pre-commit-config.yaml
.readthedocs.yaml
CHANGELOG.md
CITATION.cff
LICENSE
MANIFEST.in
README.md
codecov.yaml
pyproject.toml
.github/ISSUE_TEMPLATE/bug_report.md
.github/ISSUE_TEMPLATE/feature_request.md
.github/workflows/ci.yaml
.github/workflows/ci_fixed.yaml
.github/workflows/publish.yaml
docs/Makefile
docs/conf.py
docs/index.rst
docs/make.bat
docs/_static/favicon.ico
docs/_static/logo.png
scripts/prepare_reduced_hip.py
tests/__init__.py
tests/test_catalog.py
tests/test_cli.py
tests/test_distortion.py
tests/test_pointing.py
tests/test_util.py
tests/test_visualize.py
thuban/__init__.py
thuban/catalog.py
thuban/cli.py
thuban/distortion.py
thuban/error.py
thuban/pointing.py
thuban/simulate.py
thuban/util.py
thuban/visualize.py
thuban.egg-info/PKG-INFO
thuban.egg-info/SOURCES.txt
thuban.egg-info/dependency_links.txt
thuban.egg-info/entry_points.txt
thuban.egg-info/requires.txt
thuban.egg-info/top_level.txt
thuban/data/reduced_hip.csv