Metadata-Version: 2.4
Name: thuban
Version: 0.0.8
Summary: High precision and accuracy astrometric image solving from a guess
Author-email: "J. Marcus Hughes" <hughes.jmb@gmail.com>
Maintainer-email: "J. Marcus Hughes" <hughes.jmb@gmail.com>
Project-URL: Homepage, https://example.com
Project-URL: Documentation, https://readthedocs.org
Project-URL: Repository, https://github.com/punch-mission/thuban.git
Project-URL: Bug Tracker, https://github.com/punch-mission/thuban/issues
Project-URL: Changelog, https://github.com/punch-mission/thuban/blob/main/CHANGELOG.md
Keywords: thuban,solar,physics,analysis,astrometry,astronomy
Classifier: Development Status :: 4 - Beta
Classifier: Programming Language :: Python
Requires-Python: >=3.9
License-File: LICENSE
Requires-Dist: numpy
Requires-Dist: astropy
Requires-Dist: matplotlib
Requires-Dist: pandas
Requires-Dist: sep
Requires-Dist: scipy
Requires-Dist: scikit-learn
Requires-Dist: lmfit
Requires-Dist: tqdm
Requires-Dist: click
Provides-Extra: test
Requires-Dist: pytest; extra == "test"
Requires-Dist: pytest-doctestplus; extra == "test"
Requires-Dist: pytest-cov; extra == "test"
Requires-Dist: ruff; extra == "test"
Requires-Dist: coverage; extra == "test"
Provides-Extra: docs
Requires-Dist: sphinx; extra == "docs"
Requires-Dist: sphinx-autoapi; extra == "docs"
Requires-Dist: sphinx-automodapi; extra == "docs"
Requires-Dist: pydata-sphinx-theme; extra == "docs"
Requires-Dist: sphinx-favicon; extra == "docs"
Requires-Dist: ipython; extra == "docs"
Requires-Dist: packaging; extra == "docs"
Dynamic: license-file
